voxta_twitch_relay/__init__.py
voxta_twitch_relay/bot.py
voxta_twitch_relay/main.py
voxta_twitch_relay/webapp.py
voxta_twitch_relay-0.1.0.dist-info/licenses/LICENSE
voxta_twitch_relay-0.1.0.dist-info/METADATA
voxta_twitch_relay-0.1.0.dist-info/WHEEL
voxta_twitch_relay-0.1.0.dist-info/entry_points.txt
voxta_twitch_relay-0.1.0.dist-info/top_level.txt
voxta_twitch_relay-0.1.0.dist-info/RECORD
