Metadata-Version: 2.4
Name: voxta-twitch-relay
Version: 0.1.0
Summary: A relay app that bridges Twitch chat with the Voxta conversational AI platform via Voxta Gateway.
Author: Dion Labs
License: MIT
Project-URL: Homepage, https://github.com/dion-labs/voxta-twitch-relay
Project-URL: Documentation, https://twitch.voxta.dionlabs.ai
Classifier: Development Status :: 4 - Beta
Classifier: Intended Audience :: Developers
Classifier: Programming Language :: Python :: 3
Classifier: Programming Language :: Python :: 3.10
Classifier: Programming Language :: Python :: 3.11
Classifier: Programming Language :: Python :: 3.12
Classifier: Operating System :: OS Independent
Classifier: Topic :: Scientific/Engineering :: Artificial Intelligence
Classifier: Topic :: Communications :: Chat
Requires-Python: >=3.10
License-File: LICENSE
Requires-Dist: twitchio<3.0.0,>=2.10.0
Requires-Dist: fastapi>=0.109.0
Requires-Dist: uvicorn[standard]>=0.27.0
Requires-Dist: python-dotenv>=1.0.0
Requires-Dist: voxta-gateway>=0.1.0
Provides-Extra: dev
Requires-Dist: ruff>=0.1.0; extra == "dev"
Requires-Dist: pre-commit>=3.5.0; extra == "dev"
Requires-Dist: pytest>=7.4.0; extra == "dev"
Requires-Dist: pytest-asyncio>=0.21.0; extra == "dev"
Requires-Dist: pytest-cov>=4.1.0; extra == "dev"
Requires-Dist: coverage-badge>=1.1.0; extra == "dev"
Provides-Extra: docs
Requires-Dist: mkdocs-material>=9.5.0; extra == "docs"
Requires-Dist: mkdocstrings[python]>=0.24.0; extra == "docs"
Requires-Dist: pymdown-extensions>=10.0; extra == "docs"
Dynamic: license-file
